aiohttp_ws/__init__.py
aiohttp_ws/actions_registry.py
aiohttp_ws/clients_ws.py
aiohttp_ws/constants.py
aiohttp_ws/exceptions.py
aiohttp_ws/messages.py
aiohttp_ws/redis.py
aiohttp_ws/service.py
aiohttp_ws/settings.py
aiohttp_ws/tests/__init__.py
aiohttp_ws/tests/test_actions_registry.py
aiohttp_ws/utils/__init__.py
aiohttp_ws/utils/format.py
aiohttp_ws/utils/inspect.py
aiohttp_ws-0.1.dev1.dist-info/LICENSE.txt
aiohttp_ws-0.1.dev1.dist-info/METADATA
aiohttp_ws-0.1.dev1.dist-info/WHEEL
aiohttp_ws-0.1.dev1.dist-info/top_level.txt
aiohttp_ws-0.1.dev1.dist-info/RECORD
